<annotation>
	<folder>my-project-name</folder>
	<filename>etsy_invoice014.png</filename>
	<path>/my-project-name/etsy_invoice014.png</path>
	<source>
		<database>Unspecified</database>
	</source>
	<size>
		<width>417</width>
		<height>587</height>
		<depth>3</depth>
	</size>
	<object>
		<name>Table</name>
		<pose>Unspecified</pose>
		<truncated>0</truncated>
		<difficult>0</difficult>
		<bndbox>
			<xmin>31</xmin>
			<ymin>182</ymin>
			<xmax>409</xmax>
			<ymax>333</ymax>
		</bndbox>
	</object>
</annotation>