<annotation>
	<folder>my-project-name</folder>
	<filename>etsy_invoice004.png</filename>
	<path>/my-project-name/etsy_invoice004.png</path>
	<source>
		<database>Unspecified</database>
	</source>
	<size>
		<width>419</width>
		<height>591</height>
		<depth>3</depth>
	</size>
	<object>
		<name>Table</name>
		<pose>Unspecified</pose>
		<truncated>0</truncated>
		<difficult>0</difficult>
		<bndbox>
			<xmin>29</xmin>
			<ymin>193</ymin>
			<xmax>404</xmax>
			<ymax>374</ymax>
		</bndbox>
	</object>
</annotation>